pix_apidata/__init__.py
pix_apidata/apidata_lib.py
pix_apidata/apidata_models.py
pix_apidata-1.3.4.dist-info/METADATA
pix_apidata-1.3.4.dist-info/WHEEL
pix_apidata-1.3.4.dist-info/top_level.txt
pix_apidata-1.3.4.dist-info/RECORD
