Metadata-Version: 2.1
Name: pix_apidata
Version: 1.3.4
Summary: Python library to connect and stream the market data.
Home-page: https://github.com/pscoumar
Author: Coumar Pandourangane
Author-email: pscoumar@gmail.com
License: MIT
Keywords: stock market,apidata,accelpix,ticanalytics
Classifier: License :: OSI Approved :: MIT License
Classifier: Programming Language :: Python :: 3
Classifier: Programming Language :: Python :: 3.8
Requires-Dist: websockets==10.0.0
Requires-Dist: signalrcore-async
Requires-Dist: urllib3
